Workbook

Sheet Start Here
A1: ActivePayOS Budget Sheet
A2: Pre-filled military pay budget. Change blue input cells as needed. Monthly view; always compare against your LES, myPay, and official sources.
A4: Inputs | D4: Monthly Pay (auto-filled from ActivePayOS export) | G4: Hybrid Budget Targets (editable)
A5: Year | B5: 2026 | D5: Base Pay (taxable) | E5: 0 | G5: Housing target = % of BAH | H5: 1
A6: Pay Grade (e.g., O-1, E-5) | B6: O-1 | D6: BAH (usually non-taxable) | E6: 0 | G6: Food target = % of BAS | H6: 1
A7: Years of Service bracket | B7: < 2 | D7: BAS (usually non-taxable) | E7: 0 | G7: Minimum savings rate | H7: 0.2
A8: Duty ZIP (5-digit) | B8: 02139 | D8: Other Income (manual) | E8: 0
A9: With dependents? (TRUE/FALSE) | B9: FALSE | C9: Select TRUE for with-dependents BAH. | D9: Total Monthly Income | E9: =SUM(E5:E8) -> 0 | G9: Suggested Housing Budget | H9: =E6*H5 -> 0
A10: State of legal residence | B10: Not selected | C10: From the pay calculator. Check your LES and myPay state withholding settings. | G10: Suggested Food Budget | H10: =E7*H6 -> 0
A11: State income tax rate (optional rough estimate) | B11: 0 | C11: Optional only. ActivePayOS does not estimate state withholding yet. | D11: Estimated State Tax (optional rough) | E11: =E5*B11 | G11: Suggested Minimum Savings | H11: =E9*H7 -> 0
A12: TSP contribution % (0-1) | B12: 0.1 | C12: Optional: used for suggested TSP planning. | D12: Net After Optional State Tax | E12: =E9-E11
A13: Roth/Traditional note | B13: Roth / Traditional (your choice)
A14: Notes
A15: • Base Pay is taxable. BAH/BAS are generally non-taxable for most service members. • State of legal residence may differ from duty ZIP, duty station, and home of record. Check LES/myPay. • This workbook is monthly. Blue cells are editable planning inputs. • Hybrid approach: housing target ties to BAH, food ties to BAS, and savings uses a baseline rate. • You can override line items in the Budget tab.

Sheet Budget
A1: Monthly Budget
A2: Plan vs Actual. Blue cells are your inputs. Totals & Remaining update automatically.
A4: Monthly Income (from Start Here)
A5: Category | B5: Planned | C5: Actual | D5: Diff
A6: Income | B6: ='Start Here'!E9 -> 0 | C6: ='Start Here'!E9 -> 0 | D6: =C6-B6 -> 0
A8: Category | B8: Planned | C8: Actual | D8: Diff
A9: HOUSING (targeted to BAH)
A10: Rent / Mortgage | B10: ='Start Here'!H9 -> 0 | C10: 0 | D10: =C10-B10 -> 0
A11: Renter/Home Insurance | B11: 0 | C11: 0 | D11: =C11-B11 -> 0
A12: Utilities (electric/gas/water) | B12: 0 | C12: 0 | D12: =C12-B12 -> 0
A13: Internet | B13: 0 | C13: 0 | D13: =C13-B13 -> 0
A14: HOA / Fees | B14: 0 | C14: 0 | D14: =C14-B14 -> 0
A15: Maintenance / Repairs | B15: 0 | C15: 0 | D15: =C15-B15 -> 0
A16: Section Total | B16: =SUM(B10:B15) -> 0 | C16: =SUM(C10:C15) -> 0 | D16: =C16-B16 -> 0
A18: FOOD (targeted to BAS)
A19: Groceries | B19: ='Start Here'!H10 -> 0 | C19: 0 | D19: =C19-B19 -> 0
A20: Dining Out | B20: 0 | C20: 0 | D20: =C20-B20 -> 0
A21: Coffee / Snacks | B21: 0 | C21: 0 | D21: =C21-B21 -> 0
A22: Section Total | B22: =SUM(B19:B21) -> 0 | C22: =SUM(C19:C21) -> 0 | D22: =C22-B22 -> 0
A24: TRANSPORTATION
A25: Car payment | B25: 0 | C25: 0 | D25: =C25-B25 -> 0
A26: Gas / Transit | B26: 0 | C26: 0 | D26: =C26-B26 -> 0
A27: Car insurance | B27: 0 | C27: 0 | D27: =C27-B27 -> 0
A28: Parking / Tolls | B28: 0 | C28: 0 | D28: =C28-B28 -> 0
A29: Maintenance | B29: 0 | C29: 0 | D29: =C29-B29 -> 0
A30: Section Total | B30: =SUM(B25:B29) -> 0 | C30: =SUM(C25:C29) -> 0 | D30: =C30-B30 -> 0
A32: HEALTH & INSURANCE
A33: Medical / Dental out-of-pocket | B33: 0 | C33: 0 | D33: =C33-B33 -> 0
A34: Gym / Fitness | B34: 0 | C34: 0 | D34: =C34-B34 -> 0
A35: Life insurance | B35: 0 | C35: 0 | D35: =C35-B35 -> 0
A36: Section Total | B36: =SUM(B33:B35) -> 0 | C36: =SUM(C33:C35) -> 0 | D36: =C36-B36 -> 0
A38: DEBT PAYDOWN
A39: Credit cards (beyond minimum) | B39: 0 | C39: 0 | D39: =C39-B39 -> 0
A40: Student loans | B40: 0 | C40: 0 | D40: =C40-B40 -> 0
A41: Personal/Auto loan extra | B41: 0 | C41: 0 | D41: =C41-B41 -> 0
A42: Section Total | B42: =SUM(B39:B41) -> 0 | C42: =SUM(C39:C41) -> 0 | D42: =C42-B42 -> 0
A44: SAVINGS & INVESTING (targeted to min savings)
A45: TSP (auto from %) | B45: ='Start Here'!E5*'Start Here'!B11 -> 0 | C45: 0 | D45: =C45-B45 -> 0
A46: Roth IRA / IRA | B46: 0 | C46: 0 | D46: =C46-B46 -> 0
A47: Brokerage | B47: 0 | C47: 0 | D47: =C47-B47 -> 0
A48: Emergency fund | B48: 0 | C48: 0 | D48: =C48-B48 -> 0
A49: Sinking funds (gifts/PCS/travel) | B49: 0 | C49: 0 | D49: =C49-B49 -> 0
A50: Section Total | B50: =SUM(B45:B49) -> 0 | C50: =SUM(C45:C49) -> 0 | D50: =C50-B50 -> 0
A52: WANTS & LIFESTYLE
A53: Subscriptions | B53: 0 | C53: 0 | D53: =C53-B53 -> 0
A54: Shopping | B54: 0 | C54: 0 | D54: =C54-B54 -> 0
A55: Entertainment | B55: 0 | C55: 0 | D55: =C55-B55 -> 0
A56: Travel | B56: 0 | C56: 0 | D56: =C56-B56 -> 0
A57: Hobbies | B57: 0 | C57: 0 | D57: =C57-B57 -> 0
A58: Section Total | B58: =SUM(B53:B57) -> 0 | C58: =SUM(C53:C57) -> 0 | D58: =C58-B58 -> 0
A60: KIDS / FAMILY (if applicable)
A61: Childcare | B61: 0 | C61: 0 | D61: =C61-B61 -> 0
A62: School / activities | B62: 0 | C62: 0 | D62: =C62-B62 -> 0
A63: Diapers / supplies | B63: 0 | C63: 0 | D63: =C63-B63 -> 0
A64: Section Total | B64: =SUM(B61:B63) -> 0 | C64: =SUM(C61:C63) -> 0 | D64: =C64-B64 -> 0
A66: OTHER
A67: Phone | B67: 0 | C67: 0 | D67: =C67-B67 -> 0
A68: Charity | B68: 0 | C68: 0 | D68: =C68-B68 -> 0
A69: Misc | B69: 0 | C69: 0 | D69: =C69-B69 -> 0
A70: Section Total | B70: =SUM(B67:B69) -> 0 | C70: =SUM(C67:C69) -> 0 | D70: =C70-B70 -> 0
A72: TOTAL SPENDING | B72: =SUM($B$16,$B$22,$B$30,$B$36,$B$42,$B$50,$B$58,$B$64,$B$70) -> 0 | C72: =SUM($C$16,$C$22,$C$30,$C$36,$C$42,CB$50,$C$58,$C$64,$C$70) -> 0 | D72: =C72-B72 -> 0
A73: REMAINING (Income - Spending) | B73: =B6-B72 -> 0 | C73: =C6-C72 -> 0 | D73: =C73-B73 -> 0

Sheet Bills & Due Dates
A1: Bills & Due Dates
A2: Track recurring bills so your budget is predictable. Fill in the blue cells.
A4: Bill | B4: Amount | C4: Due Day | D4: Autopay? | E4: Account | F4: Category | G4: Notes
A5: Rent/Mortgage | D5: TRUE | F5: Housing
A6: Utilities | D6: FALSE | F6: Housing
A7: Internet | D7: TRUE | F7: Housing
A8: Phone | D8: TRUE | F8: Other
A9: Car payment | D9: TRUE | F9: Transportation
A10: Car insurance | D10: TRUE | F10: Transportation
A11: Subscriptions | D11: TRUE | F11: Wants
A20: Total Monthly Bills | B20: =SUM(B5:B200)

Sheet Goals
A1: Goals
A2: Turn big goals into a timeline. Fill in blue inputs; timeline updates automatically.
A4: Goal | B4: Target ($) | C4: Current ($) | D4: Monthly ($) | E4: Months to Goal | F4: Notes
A5: Starter emergency fund | B5: 1000 | D5: 50 | E5: =IF(D5<=0,"",IF(B5<=C5,0,CEILING((B5-C5)/D5,1))) -> 20
A6: 1 month expenses | B6: 3000 | C6: 0 | D6: 200 | E6: =IF(D6<=0,"",IF(B6<=C6,0,CEILING((B6-C6)/D6,1))) -> 15
A7: Pay off high-interest debt | B7: 2000 | C7: 0 | D7: 150 | E7: =IF(D7<=0,"",IF(B7<=C7,0,CEILING((B7-C7)/D7,1))) -> 14
A8: Down payment / house fund | B8: 20000 | C8: 0 | D8: 500 | E8: =IF(D8<=0,"",IF(B8<=C8,0,CEILING((B8-C8)/D8,1))) -> 40
A9: Big purchase (car/PCS) | B9: 5000 | C9: 0 | D9: 150 | E9: =IF(D9<=0,"",IF(B9<=C9,0,CEILING((B9-C9)/D9,1))) -> 34
